django_triflesoft_statsd-0.4.1610232024.dist-info/DESCRIPTION.rst
django_triflesoft_statsd-0.4.1610232024.dist-info/METADATA
django_triflesoft_statsd-0.4.1610232024.dist-info/metadata.json
django_triflesoft_statsd-0.4.1610232024.dist-info/RECORD
django_triflesoft_statsd-0.4.1610232024.dist-info/top_level.txt
django_triflesoft_statsd-0.4.1610232024.dist-info/WHEEL
statsd/middleware.py
statsd/__init__.py
