Metadata-Version: 2.0
Name: django-triflesoft-statsd
Version: 0.4.1610232024
Summary: Django statsd middleware by TrifleSoft
Home-page: https://bitbucket.org/triflesoft/django-statsd
Author: TrifleSoft LLC
Author-email: support@triflesoft.org
License: BSD
Keywords: django statsd triflesoft
Platform: UNKNOWN
Classifier: Development Status :: 5 - Production/Stable
Classifier: Environment :: No Input/Output (Daemon)
Classifier: Framework :: Django
Classifier: Framework :: Django :: 1.10
Classifier: Intended Audience :: Developers
Classifier: License :: OSI Approved :: BSD License
Classifier: Operating System :: POSIX :: Linux
Classifier: Programming Language :: Python :: 3 :: Only
Classifier: Programming Language :: Python :: 3.4
Classifier: Programming Language :: Python :: 3.5
Requires-Dist: django
